mkdocs_extra_sass_plugin/__init__.py
mkdocs_extra_sass_plugin/plugin.py
mkdocs_extra_sass_plugin-0.1.0.dist-info/entry_points.txt
mkdocs_extra_sass_plugin-0.1.0.dist-info/LICENSE.md
mkdocs_extra_sass_plugin-0.1.0.dist-info/WHEEL
mkdocs_extra_sass_plugin-0.1.0.dist-info/METADATA
mkdocs_extra_sass_plugin-0.1.0.dist-info/RECORD
