Metadata-Version: 2.1
Name: mkdocs-extra-sass-plugin
Version: 0.1.0
Summary: This plugin adds stylesheets to your mkdocs site from `Sass`/`SCSS`.
Home-page: https://github.com/orzih/mkdocs-extra-sass-plugin
License: MIT
Keywords: mkdocs,css,sass,scss
Author: orzih
Author-email: orzih@mail.com
Requires-Python: >=3.6
Classifier: Development Status :: 4 - Beta
Classifier: Intended Audience :: Developers
Classifier: Intended Audience :: Information Technology
Classifier: License :: OSI Approved :: MIT License
Classifier: Programming Language :: Python :: 3
Classifier: Programming Language :: Python :: 3 :: Only
Classifier: Programming Language :: Python :: 3.6
Classifier: Programming Language :: Python :: 3.7
Classifier: Programming Language :: Python :: 3.8
Classifier: Programming Language :: Python :: 3.9
Requires-Dist: beautifulsoup4 (>=4.6.3)
Requires-Dist: libsass (>=0.15)
Requires-Dist: mkdocs (>=1.1)
Project-URL: Repository, https://github.com/orzih/mkdocs-extra-sass-plugin
